xy_configure/Configure.py
xy_configure/__init__.py
xy_configure/Format/ConfigFormat.py
xy_configure/Format/__init__.py
xy_configure/Format/__pycache__/ConfigFormat.cpython-312.pyc
xy_configure/Format/__pycache__/__init__.cpython-312.pyc
xy_configure/Pair/Option.py
xy_configure/Pair/Pair.py
xy_configure/Pair/PairDelegate.py
xy_configure/Pair/Section.py
xy_configure/Pair/__init__.py
xy_configure/Raw/Raw.py
xy_configure/Raw/__init__.py
xy_configure/Raw/Format/Ini.py
xy_configure/Raw/Format/Json.py
xy_configure/Raw/Format/Toml.py
xy_configure/Raw/Format/Xml.py
xy_configure/Raw/Format/__init__.py
xy_configure/Raw/Format/__pycache__/Ini.cpython-312.pyc
xy_configure/Raw/Format/__pycache__/Json.cpython-312.pyc
xy_configure/Raw/Format/__pycache__/Toml.cpython-312.pyc
xy_configure/Raw/Format/__pycache__/Xml.cpython-312.pyc
xy_configure/Raw/Format/__pycache__/__init__.cpython-312.pyc
xy_configure/Raw/__pycache__/Raw.cpython-312.pyc
xy_configure/Raw/__pycache__/__init__.cpython-312.pyc
xy_configure/configparser/ConfigParser.py
xy_configure/configparser/__init__.py
xy_configure/configparser/__pycache__/ConfigParser.cpython-312.pyc
xy_configure/configparser/__pycache__/__init__.cpython-312.pyc
xy_configure-1.0.5.dist-info/LICENSE
xy_configure-1.0.5.dist-info/METADATA
xy_configure-1.0.5.dist-info/WHEEL
xy_configure-1.0.5.dist-info/top_level.txt
xy_configure-1.0.5.dist-info/RECORD
