Metadata-Version: 2.1
Name: xy_configure
Version: 1.0.5
Summary: 配置解析模块
Author-email: 余洋 <yuyangit.0515@qq.com>
Classifier: Programming Language :: Python :: 3
Requires-Python: >=3.11.3
License-File: LICENSE
Requires-Dist: xy-file
